[
  {
    "method": "simpson",
    "case_name": "exp",
    "min_abs_error": 2.2222224060897133e-12,
    "max_abs_error": 3.7013462701906974e-05,
    "final_n": 256,
    "final_abs_error": 2.2222224060897133e-12,
    "observed_order": 3.9986659474020887
  },
  {
    "method": "simpson",
    "case_name": "pi_integrand",
    "min_abs_error": 0.0,
    "max_abs_error": 2.4026138813137976e-05,
    "final_n": 256,
    "final_abs_error": 0.0,
    "observed_order": 6.190258552593436
  },
  {
    "method": "simpson",
    "case_name": "sine",
    "min_abs_error": 2.520024189323067e-10,
    "max_abs_error": 0.0045597549844207386,
    "final_n": 256,
    "final_abs_error": 2.520024189323067e-10,
    "observed_order": 4.013800203992324
  },
  {
    "method": "simpson",
    "case_name": "x_squared",
    "min_abs_error": 0.0,
    "max_abs_error": 0.0,
    "final_n": 256,
    "final_abs_error": 0.0,
    "observed_order": Infinity
  }
]